{
    "version": "1.0.0",
    "summary": "triples client",
    "repository": "https://github.com/robx/noexist.git",
    "license": "BSD3",
    "source-directories": [
        "src",
        "/s/elm-edn/src",
        "/s/parser/src",
        "/s/parser/src/Parser"
    ],
    "exposed-modules": [],
    "dependencies": {
        "elm-lang/core": "5.1.1 <= v < 6.0.0",
        "elm-lang/html": "2.0.0 <= v < 3.0.0",
        "elm-lang/http": "1.0.0 <= v < 2.0.0",
        "elm-lang/svg": "2.0.0 <= v < 3.0.0",
        "elm-community/random-extra": "2.0.0 <= v < 3.0.0",
        "elm-community/list-extra": "7.0.0 <= v < 8.0.0",
        "elm-lang/navigation": "2.1.0 <= v < 3.0.0",
        "evancz/url-parser": "2.0.0 <= v < 3.0.0",
        "elm-lang/websocket": "1.0.2 <= v < 2.0.0",
        "elm-tools/parser-primitives": "1.0.0 <= v < 2.0.0"
    },
    "elm-version": "0.18.0 <= v < 0.19.0"
}
